clight/__init__.py
clight/licenses/Apache Software License
clight/licenses/BSD License
clight/licenses/GNU Affero General Public License v3
clight/licenses/GNU General Public License v3 (GPLv3)
clight/licenses/GNU Lesser General Public License v3 (LGPLv3)
clight/licenses/ISC License (ISCL)
clight/licenses/MIT License
clight/licenses/Mozilla Public License 2.0 (MPL 2.0)
clight/package/.placeholder
clight/skeleton/.gitignore
clight/skeleton/.system/imports.py
clight/skeleton/.system/index.py
clight/skeleton/.system/modules/jobs.py
clight/skeleton/.system/sources/logo.ico
clight/system/importer.py
clight/system/main.py
clight/system/modules/cli.py
clight/system/modules/semver.py
clight/system/sources/.gitlab-ci.yml
clight/system/sources/README.md
clight/system/sources/__init__.py
clight/system/sources/ansi_escape
clight/system/sources/ask.wav
clight/system/sources/done.wav
clight/system/sources/error.wav
clight/system/sources/init.py
clight/system/sources/logo.ico
clight/system/sources/main.py
clight/system/sources/ready.wav
clight/system/sources/set.wav
clight/system/sources/setup.py
clight/system/sources/start.wav
clight/system/sources/unset.wav
clight/system/sources/{{CMD}}.bat
clight/system/sources/{{module}}.py
clight/system/sources/.github/labels.yml
clight/system/sources/.github/workflows/publish.yml
clight-2.4.3.dist-info/licenses/LICENSE
clight-2.4.3.dist-info/METADATA
clight-2.4.3.dist-info/WHEEL
clight-2.4.3.dist-info/entry_points.txt
clight-2.4.3.dist-info/top_level.txt
clight-2.4.3.dist-info/RECORD
