Metadata-Version: 2.4
Name: clight
Version: 2.4.3
Summary: CLight is a Python command-line interface application. A lightweight Framework that simplifies CLI app development and the package distribution process, with automatic deployment strategies from Local, GitHub and GitLab environments.
Home-page: https://github.com/IG-onGit/CLight
Author: Irakli Gzirishvili
Author-email: gziraklirex@gmail.com
Classifier: Programming Language :: Python :: 3
Classifier: License :: OSI Approved :: MIT License
Classifier: Operating System :: Microsoft :: Windows
License-File: LICENSE
Requires-Dist: PyYAML
Requires-Dist: pygame
Requires-Dist: pyttsx3
Requires-Dist: inquirer
Requires-Dist: datetime
Requires-Dist: importlib
Requires-Dist: colored
Requires-Dist: cryptography
Requires-Dist: SpeechRecognition
Dynamic: author
Dynamic: author-email
Dynamic: classifier
Dynamic: description
Dynamic: description-content-type
Dynamic: home-page
Dynamic: license-file
Dynamic: requires-dist
Dynamic: summary
